{
  "short_name": "PWA",
  "name": "PWA Demo",
  "icons": [
    {
      "src": "/image/icons-manifest-128.png",
      "type": "image/png",
      "sizes": "128x128"
    },
    {
      "src": "/image/icons-manifest-256.png",
      "type": "image/png",
      "sizes": "256x256"
    },
    {
      "src": "/image/icons-manifest-512.png",
      "type": "image/png",
      "sizes": "512x512"
    }
  ],
  "start_url": "/",
  "background_color": "#f19999",
  "display": "standalone",
  "scope": "/",
  "theme_color": "#3367D6"
}
